actorhub/__init__.py
actorhub/client.py
actorhub/exceptions.py
actorhub/models.py
actorhub-0.1.0.dist-info/METADATA
actorhub-0.1.0.dist-info/WHEEL
actorhub-0.1.0.dist-info/licenses/LICENSE
actorhub-0.1.0.dist-info/RECORD
