Metadata-Version: 2.4
Name: actorhub
Version: 0.1.0
Summary: Official Python SDK for ActorHub.ai - Verify AI-generated content against protected identities
Project-URL: Homepage, https://actorhub.ai
Project-URL: Documentation, https://docs.actorhub.ai
Project-URL: Repository, https://github.com/actorhub/actorhub-python
Project-URL: Issues, https://github.com/actorhub/actorhub-python/issues
Author-email: "ActorHub.ai" <actorhub.ai@gmail.com>
License-Expression: MIT
License-File: LICENSE
Keywords: actorhub,ai,api,consent,deepfake,face-recognition,identity,verification
Classifier: Development Status :: 4 - Beta
Classifier: Intended Audience :: Developers
Classifier: License :: OSI Approved :: MIT License
Classifier: Operating System :: OS Independent
Classifier: Programming Language :: Python :: 3
Classifier: Programming Language :: Python :: 3.8
Classifier: Programming Language :: Python :: 3.9
Classifier: Programming Language :: Python :: 3.10
Classifier: Programming Language :: Python :: 3.11
Classifier: Programming Language :: Python :: 3.12
Classifier: Topic :: Scientific/Engineering :: Artificial Intelligence
Classifier: Topic :: Software Development :: Libraries :: Python Modules
Requires-Python: >=3.8
Requires-Dist: httpx>=0.24.0
Requires-Dist: pydantic>=2.0.0
Requires-Dist: tenacity>=8.0.0
Provides-Extra: dev
Requires-Dist: black>=23.0.0; extra == 'dev'
Requires-Dist: mypy>=1.0.0; extra == 'dev'
Requires-Dist: pytest-asyncio>=0.21.0; extra == 'dev'
Requires-Dist: pytest-cov>=4.0.0; extra == 'dev'
Requires-Dist: pytest>=7.0.0; extra == 'dev'
Requires-Dist: respx>=0.20.0; extra == 'dev'
Requires-Dist: ruff>=0.1.0; extra == 'dev'
